tap_gladly/__init__.py
tap_gladly/client.py
tap_gladly/schemas/export_conversation-all_types.json
tap_gladly/schemas/export_conversation-chat_message.json
tap_gladly/schemas/export_conversation-conversation_note.json
tap_gladly/schemas/export_conversation-conversation_status_change.json
tap_gladly/schemas/export_conversation-customer_activity.json
tap_gladly/schemas/export_conversation-email.json
tap_gladly/schemas/export_conversation-facebook_message.json
tap_gladly/schemas/export_conversation-instagram_direct.json
tap_gladly/schemas/export_conversation-phone_call.json
tap_gladly/schemas/export_conversation-sms.json
tap_gladly/schemas/export_conversation-topic_change.json
tap_gladly/schemas/export_conversation-twitter.json
tap_gladly/schemas/export_conversation-voicemail.json
tap_gladly/schemas/export_conversation-whatsapp.json
tap_gladly/schemas/export_jobs.json
tap_gladly/schemas/export_topics.json
tap_gladly/schemas/reports__conversation_timestamps_report.json
tap_gladly/streams.py
tap_gladly/tap.py
tap_gladly/tests/__init__.py
tap_gladly/tests/test_core.py
tap_gladly/tests/test_streams.py
tap_gladly-0.4.1.dist-info/entry_points.txt
tap_gladly-0.4.1.dist-info/WHEEL
tap_gladly-0.4.1.dist-info/METADATA
tap_gladly-0.4.1.dist-info/RECORD
