Metadata-Version: 2.1
Name: tap-gladly
Version: 0.4.1
Summary: `tap-gladly` is a Singer tap for gladly, built with the Meltano SDK for Singer Taps.
License: Apache 2.0
Keywords: ELT,gladly
Author: harrystech
Requires-Python: >=3.7.1,<3.11
Classifier: License :: Other/Proprietary License
Classifier: Programming Language :: Python :: 3
Classifier: Programming Language :: Python :: 3.8
Classifier: Programming Language :: Python :: 3.9
Classifier: Programming Language :: Python :: 3.10
Requires-Dist: pendulum (>=2.1.2,<3.0.0)
Requires-Dist: requests (>=2.25.1,<3.0.0)
Requires-Dist: singer-sdk (>=0.10.0,<0.11.0)
